Metadata-Version: 1.1
Name: django-http-authentication
Version: 0.0.1
Summary: A django application that adds decorators to allow authentication via HTTP_AUTHORIZATION.
Home-page: https://github.com/chwick/django-http-authorization
Author: Christoph Wick
Author-email: wick.chr.info@gmail.com
License: MIT
Platform: UNKNOWN
Classifier: Development Status :: 3 - Alpha
Classifier: Framework :: Django
Classifier: Framework :: Django :: 1.7
Classifier: Framework :: Django :: 1.8
Classifier: Framework :: Django :: 1.9
Classifier: Framework :: Django :: 1.10
Classifier: Framework :: Django :: 1.11
Classifier: Intended Audience :: Developers
Classifier: License :: OSI Approved :: MIT License
Classifier: Natural Language :: English
Classifier: Operating System :: OS Independent
Classifier: Programming Language :: Python
Classifier: Programming Language :: Python :: 2
Classifier: Programming Language :: Python :: 2.7
Classifier: Programming Language :: Python :: 3
Classifier: Programming Language :: Python :: 3.3
Classifier: Programming Language :: Python :: 3.4
Classifier: Programming Language :: Python :: 3.5
